setup.py
morfi/__init__.py
morfi/base.py
morfi/controls.py
morfi/loaders.py
morfi/meta_test.py
morfi/rules.py
morfi.egg-info/PKG-INFO
morfi.egg-info/SOURCES.txt
morfi.egg-info/dependency_links.txt
morfi.egg-info/requires.txt
morfi.egg-info/top_level.txt
orioniface/__init__.py
orioniface/controllers.py