Metadata-Version: 1.0
Name: morfi
Version: 0.0.1
Summary: RC Online services library
Home-page: https://github.com/keydach/morfi
Author: Pavel Merzlyakov
Author-email: merzlyakovpavel@gmail.com
License: LGPLv3
Platform: UNKNOWN
